TestrailLibrary/TestrailLibrary.py
TestrailLibrary/__init__.py
TestrailLibrary/testrail.py
tests/__init__.py
tests/mock_responses.py
tests/test_regression.py
robotframework_testrail_library_nerajarolle-0.0.8.dist-info/LICENSE
robotframework_testrail_library_nerajarolle-0.0.8.dist-info/METADATA
robotframework_testrail_library_nerajarolle-0.0.8.dist-info/WHEEL
robotframework_testrail_library_nerajarolle-0.0.8.dist-info/top_level.txt
robotframework_testrail_library_nerajarolle-0.0.8.dist-info/RECORD
