Metadata-Version: 2.1
Name: robotframework-testrail-library-nerajarolle
Version: 0.0.8
Summary: A robot framework library to integrate robot tests with Testrail
Home-page: https://github.com/nerajarolle/robotframework-testrail-library
Author: Alessandro Ferrante
Author-email: nerajarolle@gmail.com
Project-URL: Bug Tracker, https://github.com/nerajarolle/robotframework-testrail-library/issues
Classifier: Programming Language :: Python :: 3
Classifier: License :: OSI Approved :: MIT License
Classifier: Operating System :: OS Independent
Requires-Python: >=3.8
License-File: LICENSE
Requires-Dist: requests
Requires-Dist: robotframework
